[
  {
    "id": "CUSTOM-Q1",
    "index": 1,
    "type": "MULTIPLE_CHOICE",
    "category": "Algebra",
    "stem": "Evaluate: 3<sup>2</sup> × 4 − 6 ÷ 3 + 5",
    "choices": [
      { "key": "A", "text": "37" },
      { "key": "B", "text": "39" },
      { "key": "C", "text": "41" },
      { "key": "D", "text": "47" }
    ],
    "answer": "B"
  },
  {
    "id": "CUSTOM-Q2",
    "index": 2,
    "type": "MULTIPLE_CHOICE",
    "category": "Algebra",
    "stem": "A recipe uses flour to sugar in a ratio of 5:2. If a baker uses 420 grams of flour, how many grams of sugar should be used?",
    "choices": [
      { "key": "A", "text": "160" },
      { "key": "B", "text": "168" },
      { "key": "C", "text": "175" },
      { "key": "D", "text": "210" }
    ],
    "answer": "B"
  },
  {
    "id": "CUSTOM-Q3",
    "index": 3,
    "type": "MULTIPLE_CHOICE",
    "category": "Geometry",
    "stem": "In △ABC, the exterior angle at C measures 128°. The measures of ∠A and ∠B are in the ratio 3:5. What is the measure of ∠B?",
    "choices": [
      { "key": "A", "text": "48°" },
      { "key": "B", "text": "60°" },
      { "key": "C", "text": "80°" },
      { "key": "D", "text": "96°" }
    ],
    "answer": "C"
  },
  {
    "id": "CUSTOM-Q4",
    "index": 4,
    "type": "MULTIPLE_CHOICE",
    "category": "Statistics",
    "stem": "A bag contains 3 red, 5 blue, and 2 green marbles. If 2 marbles are drawn at random without replacement, what is the probability that both are red?",
    "choices": [
      { "key": "A", "text": "1/5" },
      { "key": "B", "text": "1/15" },
      { "key": "C", "text": "1/9" },
      { "key": "D", "text": "2/15" }
    ],
    "answer": "B"
  },
  {
    "id": "CUSTOM-Q5",
    "index": 5,
    "type": "MULTIPLE_CHOICE",
    "category": "Algebra",
    "stem": "Simplify: (3<sup>2</sup> · 3<sup>4</sup>) ÷ 3<sup>3</sup>",
    "choices": [
      { "key": "A", "text": "3" },
      { "key": "B", "text": "9" },
      { "key": "C", "text": "27" },
      { "key": "D", "text": "81" }
    ],
    "answer": "C"
  },
  {
    "id": "CUSTOM-Q6",
    "index": 6,
    "type": "MULTIPLE_CHOICE",
    "category": "Algebra",
    "stem": "The solutions to |2x − 3| = 9 are x = 6 and x = −3. What is the sum of the solutions?",
    "choices": [
      { "key": "A", "text": "−3" },
      { "key": "B", "text": "0" },
      { "key": "C", "text": "3" },
      { "key": "D", "text": "9" }
    ],
    "answer": "C"
  },
  {
    "id": "CUSTOM-Q7",
    "index": 7,
    "type": "MULTIPLE_CHOICE",
    "category": "Algebra",
    "stem": "Solve the inequality: 4(2x − 3) ≤ 5x + 6. What is the greatest integer solution?",
    "choices": [
      { "key": "A", "text": "4" },
      { "key": "B", "text": "5" },
      { "key": "C", "text": "6" },
      { "key": "D", "text": "7" }
    ],
    "answer": "C"
  },
  {
    "id": "CUSTOM-Q8",
    "index": 8,
    "type": "MULTIPLE_CHOICE",
    "category": "Geometry",
    "stem": "A right rectangular prism has dimensions 4 cm by 3 cm by h cm. Its volume is 120 cm<sup>3</sup>. What is h?",
    "choices": [
      { "key": "A", "text": "8" },
      { "key": "B", "text": "9" },
      { "key": "C", "text": "10" },
      { "key": "D", "text": "12" }
    ],
    "answer": "C"
  },
  {
    "id": "CUSTOM-Q9",
    "index": 9,
    "type": "MULTIPLE_CHOICE",
    "category": "Statistics",
    "stem": "Ten students’ scores are: 75, 80, 80, 85, 90, 90, 90, 92, 95, 95. What is the median?",
    "choices": [
      { "key": "A", "text": "85" },
      { "key": "B", "text": "88.5" },
      { "key": "C", "text": "90" },
      { "key": "D", "text": "91" }
    ],
    "answer": "C"
  },
  {
    "id": "CUSTOM-Q10",
    "index": 10,
    "type": "MULTIPLE_CHOICE",
    "category": "Statistics",
    "stem": "From a group of 8 students, how many different 3-student committees can be formed?",
    "choices": [
      { "key": "A", "text": "24" },
      { "key": "B", "text": "56" },
      { "key": "C", "text": "64" },
      { "key": "D", "text": "336" }
    ],
    "answer": "B"
  }
]
